loguru/__init__.py
loguru/__init__.pyi
loguru/_asyncio_loop.py
loguru/_better_exceptions.py
loguru/_colorama.py
loguru/_colorizer.py
loguru/_contextvars.py
loguru/_ctime_functions.py
loguru/_datetime.py
loguru/_defaults.py
loguru/_error_interceptor.py
loguru/_file_sink.py
loguru/_filters.py
loguru/_get_frame.py
loguru/_handler.py
loguru/_locks_machinery.py
loguru/_logger.py
loguru/_recattrs.py
loguru/_simple_sinks.py
loguru/_string_parsers.py
loguru/py.typed
loguru_zopyx-0.7.2.dist-info/WHEEL
loguru_zopyx-0.7.2.dist-info/METADATA
loguru_zopyx-0.7.2.dist-info/RECORD
